README.md
setup.py
ccprocesspool/__init__.py
ccprocesspool.egg-info/PKG-INFO
ccprocesspool.egg-info/SOURCES.txt
ccprocesspool.egg-info/dependency_links.txt
ccprocesspool.egg-info/not-zip-safe
ccprocesspool.egg-info/top_level.txt