Metadata-Version: 2.1
Name: ccprocesspool
Version: 2.1
Summary: Process pool to add/check/stop all processes in pool
Home-page: UNKNOWN
Author: OpenFibers
Author-email: openfibers@gmail.com
License: MIT
Platform: UNKNOWN
